tag_utils/__init__.py
tag_utils/basic.py
tag_utils/common.py
tag_utils/compose.py
tag_utils/delta.py
tag_utils/et.py
tag_utils/koji.py
tag_utils/cli/__init__.py
tag_utils/cli/tag_cleaner.py
tag_utils/cli/tag_delta.py
tag_utils/cli/tag_over.py
tag_utils-0.0.8.data/data/LICENSE
tag_utils-0.0.8.dist-info/AUTHORS.rst
tag_utils-0.0.8.dist-info/LICENSE
tag_utils-0.0.8.dist-info/METADATA
tag_utils-0.0.8.dist-info/WHEEL
tag_utils-0.0.8.dist-info/entry_points.txt
tag_utils-0.0.8.dist-info/top_level.txt
tag_utils-0.0.8.dist-info/RECORD
