Metadata-Version: 2.1
Name: tag-utils
Version: 0.0.8
Summary: tag_utils is a collection of Pungi compose and Koji tag functions for release-depot.
Home-page: http://github.com/release-depot/tag-utils
Author: Red Hat
Author-email: lon@metamorphism.com
Maintainer: Lon Hohberger
Maintainer-email: lon@metamorphism.com
License: MIT
Platform: UNKNOWN
Classifier: Development Status :: 4 - Beta
Classifier: Intended Audience :: Developers
Classifier: Natural Language :: English
Classifier: Operating System :: POSIX :: Linux
Classifier: Programming Language :: Python :: 3
Classifier: Programming Language :: Python :: 3.6
Classifier: Programming Language :: Python :: 3.7
Classifier: Topic :: Software Development
Classifier: Topic :: Software Development :: Libraries
Classifier: Topic :: Software Development :: Libraries :: Python Modules
Classifier: Topic :: Utilities
License-File: LICENSE
License-File: AUTHORS.rst
Requires-Dist: pyyaml
Requires-Dist: koji
Requires-Dist: toolchest (>=0.0.6)
Requires-Dist: koji-wrapper
Provides-Extra: docs
Requires-Dist: sphinx ; extra == 'docs'
Requires-Dist: sphinx-autobuild ; extra == 'docs'
Requires-Dist: sphinx-rtd-theme ; extra == 'docs'
Provides-Extra: test
Requires-Dist: coverage ; extra == 'test'
Requires-Dist: flake8 ; extra == 'test'
Requires-Dist: pytest ; extra == 'test'
Requires-Dist: pytest-datadir ; extra == 'test'
Requires-Dist: tox ; extra == 'test'
